{
  "class": "org.batfish.question.ospfprocess.OspfProcessConfigurationQuestion",
  "differential": false,
  "instance": {
    "description": "Returns configuration parameters for OSPF routing processes.",
    "instanceName": "__ospfProcessConfiguration_e794f529-380a-42f0-b5ae-ae2aed12c0aa",
    "longDescription": "Returns the values of important properties for all OSPF processes running across the network.",
    "orderedVariableNames": [
      "nodes",
      "properties"
    ],
    "tags": [
      "configuration",
      "ospf"
    ],
    "variables": {
      "nodes": {
        "description": "Include nodes matching this name or regex.",
        "displayName": "Nodes",
        "optional": true,
        "type": "nodeSpec",
        "value": "ciscoasa"
      },
      "properties": {
        "description": "Include properties matching this regex.",
        "displayName": "Properties",
        "optional": true,
        "type": "ospfPropertySpec"
      }
    }
  },
  "nodes": "${nodes}",
  "properties": "${properties}"
}